{
  "nodes": [
    [
      4,
      {
        "id": 4,
        "x": -42.09203286680395,
        "y": -32.95632768480789,
        "text": "Root",
        "size": "md",
        "color": "none",
        "w": 80,
        "h": 51,
        "width": 80,
        "height": 51
      }
    ],
    [
      12,
      {
        "id": 12,
        "x": 1962.7111572731633,
        "y": -676.3290338023363,
        "text": "Geometry\nNodes",
        "color": "#6366f1",
        "fontSize": 15,
        "align": "center",
        "bold": false,
        "italic": false,
        "width": 107.86853621919376,
        "height": 78.25756549235626,
        "w": 108,
        "h": 78
      }
    ],
    [
      14,
      {
        "id": 14,
        "x": 1402.8010107866864,
        "y": -749.6155743434323,
        "text": "Procedural",
        "color": "#06b6d4",
        "fontSize": 15,
        "align": "center",
        "bold": false,
        "italic": false,
        "width": 113.1562095632719,
        "height": 56.04933744722814,
        "w": 113,
        "h": 56
      }
    ],
    [
      15,
      {
        "id": 15,
        "x": 1782.0584414181203,
        "y": -903.0537029415589,
        "text": "Shaders",
        "color": "#22c55e",
        "fontSize": 15,
        "align": "center",
        "bold": false,
        "italic": false,
        "width": 94.12058552459064,
        "height": 56.04933744722814,
        "w": 94,
        "h": 56
      }
    ],
    [
      16,
      {
        "id": 16,
        "x": 705.3899288639552,
        "y": -341.35993938394677,
        "text": "Game Development",
        "color": "#f59e0b",
        "fontSize": 15,
        "align": "center",
        "bold": false,
        "italic": false,
        "width": 131.1342989331375,
        "height": 78.25756549235626,
        "w": 131,
        "h": 78
      }
    ],
    [
      21,
      {
        "id": 21,
        "x": 1072.763348635167,
        "y": -677.3501845813486,
        "text": "Animation",
        "color": "#22c55e",
        "fontSize": 15,
        "align": "center",
        "bold": false,
        "italic": false,
        "width": 109.98360555682503,
        "height": 56.04933744722814,
        "w": 110,
        "h": 56
      }
    ],
    [
      23,
      {
        "id": 23,
        "x": 1089.845041776057,
        "y": -158.9401343858071,
        "text": "Programming",
        "color": "#6366f1",
        "fontSize": 15,
        "align": "center",
        "bold": false,
        "italic": false,
        "width": 134.3069029395844,
        "height": 56.04933744722814,
        "w": 134,
        "h": 56
      }
    ],
    [
      24,
      {
        "id": 24,
        "x": 728.9744494794265,
        "y": -38.65377090967334,
        "text": "Audio",
        "color": "#06b6d4",
        "fontSize": 15,
        "align": "center",
        "bold": false,
        "italic": false,
        "width": 84.60277350525,
        "height": 56.04933744722814,
        "w": 85,
        "h": 56
      }
    ],
    [
      26,
      {
        "id": 26,
        "x": 1318.6831165074552,
        "y": -592.9415869027646,
        "text": "Level Design",
        "color": "#06b6d4",
        "fontSize": 15,
        "align": "center",
        "bold": false,
        "italic": false,
        "width": 86.71784284288127,
        "height": 78.25756549235626,
        "w": 87,
        "h": 78
      }
    ],
    [
      27,
      {
        "id": 27,
        "x": 1658.0977746506546,
        "y": -341.35993938394677,
        "text": "Props & Environment",
        "color": "#6366f1",
        "fontSize": 15,
        "align": "center",
        "bold": false,
        "italic": false,
        "width": 126.90416025787499,
        "height": 78.25756549235626,
        "w": 127,
        "h": 78
      }
    ],
    [
      28,
      {
        "id": 28,
        "x": 1968.963386938107,
        "y": -438.20051784716645,
        "text": "CSG",
        "color": "#8B5CF6",
        "fontSize": 15,
        "align": "center",
        "bold": false,
        "italic": false,
        "width": 84.60277350525,
        "height": 56.04933744722814,
        "w": 85,
        "h": 56
      }
    ],
    [
      29,
      {
        "id": 29,
        "x": 1277.511555386509,
        "y": -1205.903502066148,
        "text": "Character Design",
        "color": "#06b6d4",
        "fontSize": 15,
        "align": "center",
        "bold": false,
        "italic": false,
        "width": 105.7534668815625,
        "height": 78.25756549235626,
        "w": 106,
        "h": 78
      }
    ],
    [
      30,
      {
        "id": 30,
        "x": 719.3899288639552,
        "y": -615.6897380243636,
        "text": "Narrative & Writing",
        "color": "#8B5CF6",
        "fontSize": 15,
        "align": "center",
        "bold": false,
        "italic": false,
        "width": 102.58086287511564,
        "height": 100.46579353748439,
        "w": 103,
        "h": 100
      }
    ],
    [
      34,
      {
        "id": 34,
        "x": 1504.3147023413856,
        "y": -1320.1846236121562,
        "text": "Rigging/Animation",
        "color": "#06b6d4",
        "fontSize": 15,
        "align": "center",
        "bold": false,
        "italic": false,
        "width": 109.98360555682503,
        "height": 78.25756549235626,
        "w": 110,
        "h": 78
      }
    ],
    [
      36,
      {
        "id": 36,
        "x": 1510.5888273413857,
        "y": -1071.7315243819528,
        "text": "Modeling",
        "color": "#8B5CF6",
        "fontSize": 15,
        "align": "center",
        "bold": false,
        "italic": false,
        "width": 103.63839754393126,
        "height": 56.04933744722814,
        "w": 104,
        "h": 56
      }
    ],
    [
      38,
      {
        "id": 38,
        "x": 1341.3167580218467,
        "y": -157.8041317957719,
        "text": "Mechanics",
        "color": "#22c55e",
        "fontSize": 15,
        "align": "center",
        "bold": false,
        "italic": false,
        "width": 112.09867489445628,
        "height": 56.04933744722814,
        "w": 112,
        "h": 56
      }
    ],
    [
      39,
      {
        "id": 39,
        "x": 1726.5901542517918,
        "y": -1449.8923117918746,
        "text": "Armature Deform",
        "color": "#6366f1",
        "fontSize": 15,
        "align": "center",
        "bold": false,
        "italic": false,
        "width": 104.69593221274688,
        "height": 78.25756549235626,
        "w": 105,
        "h": 78
      }
    ],
    [
      40,
      {
        "id": 40,
        "x": 1720.8416769589944,
        "y": -1214.23206957898,
        "text": "Blendshapes",
        "color": "#8B5CF6",
        "fontSize": 15,
        "align": "center",
        "bold": false,
        "italic": false,
        "width": 126.90416025787499,
        "height": 56.04933744722814,
        "w": 127,
        "h": 56
      }
    ],
    [
      41,
      {
        "id": 41,
        "x": 1934.6504821391793,
        "y": -1449.8923117918746,
        "text": "AccuRig/CCiC Rigify Pipeline",
        "color": "#8B5CF6",
        "fontSize": 15,
        "align": "center",
        "bold": false,
        "italic": false,
        "width": 147.3619305899211,
        "height": 77.71806905412176,
        "w": 147,
        "h": 78
      }
    ],
    [
      63,
      {
        "id": 63,
        "x": -932.7504034853443,
        "y": 956.3477513967391,
        "text": "Repetitive Tasks",
        "color": "#8B5CF6",
        "fontSize": 14,
        "align": "center",
        "bold": false,
        "italic": false,
        "width": null,
        "height": null,
        "w": 141,
        "h": 53
      }
    ],
    [
      64,
      {
        "id": 64,
        "x": -684.7638729829371,
        "y": 956.3477513967391,
        "text": "Frequency",
        "color": "#f59e0b",
        "fontSize": 14,
        "align": "center",
        "bold": false,
        "italic": false,
        "width": null,
        "height": null,
        "w": 104,
        "h": 53
      }
    ],
    [
      68,
      {
        "id": 68,
        "x": -364.77012533761877,
        "y": 681.5216311844649,
        "text": "Weekly",
        "color": "#8B5CF6",
        "fontSize": 14,
        "align": "center",
        "bold": false,
        "italic": false,
        "width": null,
        "height": null,
        "w": 83,
        "h": 53
      }
    ],
    [
      70,
      {
        "id": 70,
        "x": -251.63548026428782,
        "y": 787.9613330443265,
        "text": "Biweekly",
        "color": "#6366f1",
        "fontSize": 14,
        "align": "center",
        "bold": false,
        "italic": false,
        "width": null,
        "height": null,
        "w": 94,
        "h": 53
      }
    ],
    [
      72,
      {
        "id": 72,
        "x": -256.8251428823306,
        "y": 944.0534135425335,
        "text": "Monthly",
        "color": "#8B5CF6",
        "fontSize": 14,
        "align": "center",
        "bold": false,
        "italic": false,
        "width": null,
        "height": null,
        "w": 90,
        "h": 53
      }
    ],
    [
      73,
      {
        "id": 73,
        "x": -256.4279987702872,
        "y": 1071.4294726523863,
        "text": "Semi-monthly",
        "color": "#6366f1",
        "fontSize": 14,
        "align": "center",
        "bold": false,
        "italic": false,
        "width": null,
        "height": null,
        "w": 127,
        "h": 53
      }
    ],
    [
      74,
      {
        "id": 74,
        "x": -336.3488030881447,
        "y": 1255.143529331098,
        "text": "Yearly",
        "color": "#8B5CF6",
        "fontSize": 14,
        "align": "center",
        "bold": false,
        "italic": false,
        "width": null,
        "height": null,
        "w": 80,
        "h": 53
      }
    ],
    [
      75,
      {
        "id": 75,
        "x": -17.35883591032882,
        "y": 1071.4294726523863,
        "text": "Knife sharpening",
        "color": "#8B5CF6",
        "fontSize": 14,
        "align": "center",
        "bold": false,
        "italic": false,
        "width": null,
        "height": null,
        "w": 111,
        "h": 74
      }
    ],
    [
      77,
      {
        "id": 77,
        "x": 23.55428432018323,
        "y": 787.9613330443265,
        "text": "Laundry",
        "color": "#8B5CF6",
        "fontSize": 14,
        "align": "center",
        "bold": false,
        "italic": false,
        "width": null,
        "height": null,
        "w": 90,
        "h": 53
      }
    ],
    [
      84,
      {
        "id": 84,
        "x": 2695.405244115013,
        "y": -917.4890580233555,
        "text": "Post-processing",
        "color": "#06b6d4",
        "fontSize": 14,
        "align": "center",
        "bold": false,
        "italic": false,
        "width": null,
        "height": null,
        "w": 107,
        "h": 74
      }
    ],
    [
      85,
      {
        "id": 85,
        "x": 2980.5075134405784,
        "y": -1039.3825554997682,
        "text": "Pixelation",
        "color": "#8B5CF6",
        "fontSize": 14,
        "align": "center",
        "bold": false,
        "italic": false,
        "width": null,
        "height": null,
        "w": 100,
        "h": 53
      }
    ],
    [
      86,
      {
        "id": 86,
        "x": 2989.709185389213,
        "y": -816.2154820219718,
        "text": "Outline",
        "color": "#8B5CF6",
        "fontSize": 14,
        "align": "center",
        "bold": false,
        "italic": false,
        "width": null,
        "height": null,
        "w": 84,
        "h": 53
      }
    ],
    [
      87,
      {
        "id": 87,
        "x": 1326.5736302937275,
        "y": -336.615628384188,
        "text": "UX/UI",
        "color": "#8B5CF6",
        "fontSize": 14,
        "align": "center",
        "bold": false,
        "italic": false,
        "width": null,
        "height": null,
        "w": 80,
        "h": 53
      }
    ],
    [
      88,
      {
        "id": 88,
        "x": 621.4568425186934,
        "y": 175.80932605709415,
        "text": "SFX",
        "color": "#8B5CF6",
        "fontSize": 14,
        "align": "center",
        "bold": false,
        "italic": false,
        "width": null,
        "height": null,
        "w": 80,
        "h": 53
      }
    ],
    [
      89,
      {
        "id": 89,
        "x": 864.8374335795415,
        "y": 183.4145298222664,
        "text": "Music",
        "color": "#6366f1",
        "fontSize": 14,
        "align": "center",
        "bold": false,
        "italic": false,
        "width": null,
        "height": null,
        "w": 80,
        "h": 53
      }
    ],
    [
      94,
      {
        "id": 94,
        "x": 1162.1658373171063,
        "y": 159.71032749594048,
        "text": "Rhythm-based attacks",
        "color": "#6366f1",
        "fontSize": 14,
        "align": "center",
        "bold": false,
        "italic": false,
        "width": null,
        "height": null,
        "w": 92,
        "h": 95
      }
    ],
    [
      97,
      {
        "id": 97,
        "x": 1531.6556941592876,
        "y": 169.98267974571408,
        "text": "Planetary Environments",
        "color": "#8B5CF6",
        "fontSize": 14,
        "align": "center",
        "bold": false,
        "italic": false,
        "width": null,
        "height": null,
        "w": 127,
        "h": 74
      }
    ],
    [
      99,
      {
        "id": 99,
        "x": 851.3531345959074,
        "y": -1199.4940626389455,
        "text": "Physics Simulation",
        "color": "#8B5CF6",
        "fontSize": 15,
        "align": "center",
        "bold": false,
        "italic": false,
        "width": null,
        "height": null,
        "w": 111,
        "h": 77
      }
    ],
    [
      103,
      {
        "id": 103,
        "x": 2248.9155480703316,
        "y": -1240.1228780955107,
        "text": "Camera Occlusion",
        "color": "#22c55e",
        "fontSize": 14,
        "align": "center",
        "bold": false,
        "italic": false,
        "width": null,
        "height": null,
        "w": 100,
        "h": 74
      }
    ],
    [
      104,
      {
        "id": 104,
        "x": 2526.3743874618963,
        "y": -1366.0884647499022,
        "text": "X-Ray",
        "color": "#8B5CF6",
        "fontSize": 14,
        "align": "center",
        "bold": false,
        "italic": false,
        "width": null,
        "height": null,
        "w": 80,
        "h": 53
      }
    ],
    [
      105,
      {
        "id": 105,
        "x": 2525.377355801865,
        "y": -1240.7209728534033,
        "text": "Tunnel Cutout",
        "color": "#8B5CF6",
        "fontSize": 14,
        "align": "center",
        "bold": false,
        "italic": false,
        "width": null,
        "height": null,
        "w": 81,
        "h": 74
      }
    ],
    [
      106,
      {
        "id": 106,
        "x": 2517.6500614731685,
        "y": -1117.4477963951385,
        "text": "Camera Distance",
        "color": "#8B5CF6",
        "fontSize": 14,
        "align": "center",
        "bold": false,
        "italic": false,
        "width": null,
        "height": null,
        "w": 93,
        "h": 74
      }
    ],
    [
      107,
      {
        "id": 107,
        "x": 1642.4493665495472,
        "y": -533.3338155612142,
        "text": "Iterative",
        "color": "#06b6d4",
        "fontSize": 14,
        "align": "center",
        "bold": false,
        "italic": false,
        "width": null,
        "height": null,
        "w": 91,
        "h": 53
      }
    ],
    [
      108,
      {
        "id": 108,
        "x": 2323.513283309095,
        "y": -343.7797932111738,
        "text": "Physically Based Rendering Texturing",
        "color": "#EAB308",
        "fontSize": 14,
        "align": "center",
        "bold": false,
        "italic": false,
        "width": 177.38746712331442,
        "height": 80.20123554960271,
        "w": 177,
        "h": 80
      }
    ],
    [
      109,
      {
        "id": 109,
        "x": 2175.6133735491053,
        "y": -26.161973809541475,
        "text": "Color/Albedo",
        "color": "#8B5CF6",
        "fontSize": 14,
        "align": "center",
        "bold": false,
        "italic": false,
        "width": null,
        "height": null,
        "w": 82,
        "h": 74
      }
    ],
    [
      110,
      {
        "id": 110,
        "x": 2293.7492962354163,
        "y": 87.49910332046986,
        "text": "Roughness",
        "color": "#8B5CF6",
        "fontSize": 14,
        "align": "center",
        "bold": false,
        "italic": false,
        "width": null,
        "height": null,
        "w": 109,
        "h": 53
      }
    ],
    [
      111,
      {
        "id": 111,
        "x": 2466.4783347085836,
        "y": 83.02425776417019,
        "text": "Normal",
        "color": "#8B5CF6",
        "fontSize": 14,
        "align": "center",
        "bold": false,
        "italic": false,
        "width": null,
        "height": null,
        "w": 85,
        "h": 53
      }
    ],
    [
      112,
      {
        "id": 112,
        "x": 2587.2991647286744,
        "y": -6.4726533618229745,
        "text": "Metallic",
        "color": "#8B5CF6",
        "fontSize": 14,
        "align": "center",
        "bold": false,
        "italic": false,
        "width": null,
        "height": null,
        "w": 87,
        "h": 53
      }
    ],
    [
      113,
      {
        "id": 113,
        "x": 2199.240203854962,
        "y": -778.6647471135944,
        "text": "Reflective",
        "color": "#EAB308",
        "fontSize": 14,
        "align": "center",
        "bold": false,
        "italic": false,
        "width": null,
        "height": null,
        "w": 99,
        "h": 53
      }
    ],
    [
      114,
      {
        "id": 114,
        "x": 2567.5988723306787,
        "y": -676.7801656955821,
        "text": "CD Disc",
        "color": "#8B5CF6",
        "fontSize": 14,
        "align": "center",
        "bold": false,
        "italic": false,
        "width": null,
        "height": null,
        "w": 80,
        "h": 74
      }
    ],
    [
      115,
      {
        "id": 115,
        "x": 2549.4179866826066,
        "y": -781.5545971491568,
        "text": "Mirror",
        "color": "#8B5CF6",
        "fontSize": 14,
        "align": "center",
        "bold": false,
        "italic": false,
        "width": null,
        "height": null,
        "w": 80,
        "h": 53
      }
    ],
    [
      116,
      {
        "id": 116,
        "x": 2208.555710955165,
        "y": -527.8908373854574,
        "text": "Portals",
        "color": "#8B5CF6",
        "fontSize": 14,
        "align": "center",
        "bold": false,
        "italic": false,
        "width": null,
        "height": null,
        "w": 82,
        "h": 53
      }
    ],
    [
      117,
      {
        "id": 117,
        "x": 2467.962364789954,
        "y": -549.5483998246707,
        "text": "Water",
        "color": "#8B5CF6",
        "fontSize": 14,
        "align": "center",
        "bold": false,
        "italic": false,
        "width": null,
        "height": null,
        "w": 80,
        "h": 53
      }
    ],
    [
      118,
      {
        "id": 118,
        "x": 1352.218946641484,
        "y": 319.0498908208346,
        "text": "Expansive player controller",
        "color": "#8B5CF6",
        "fontSize": 14,
        "align": "center",
        "bold": false,
        "italic": false,
        "width": null,
        "height": null,
        "w": 102,
        "h": 95
      }
    ]
  ],
  "connections": [
    {
      "from": 12,
      "to": 14,
      "_bezier": {
        "x1": 1960.7111572731633,
        "y1": -637.3290338023363,
        "cp1x": 1810.7111572731633,
        "cp1y": -637.3290338023363,
        "cp2x": 1667.8010107866864,
        "cp2y": -721.6155743434323,
        "x2": 1517.8010107866864,
        "y2": -721.6155743434323
      }
    },
    {
      "from": 14,
      "to": 15,
      "_bezier": {
        "x1": 1517.8010107866864,
        "y1": -721.6155743434323,
        "cp1x": 1657.916383104715,
        "cp1y": -721.6155743434323,
        "cp2x": 1639.9430691000919,
        "cp2y": -875.0537029415589,
        "x2": 1780.0584414181203,
        "y2": -875.0537029415589
      }
    },
    {
      "from": 26,
      "to": 27,
      "_bezier": {
        "x1": 1407.6831165074552,
        "y1": -553.9415869027646,
        "cp1x": 1557.6831165074552,
        "cp1y": -553.9415869027646,
        "cp2x": 1506.0977746506546,
        "cp2y": -302.35993938394677,
        "x2": 1656.0977746506546,
        "y2": -302.35993938394677
      }
    },
    {
      "from": 16,
      "to": 21,
      "_bezier": {
        "x1": 838.3899288639552,
        "y1": -302.35993938394677,
        "cp1x": 943.3899288639552,
        "cp1y": -333.85993938394677,
        "cp2x": 965.763348635167,
        "cp2y": -617.8501845813486,
        "x2": 1070.763348635167,
        "y2": -649.3501845813486
      }
    },
    {
      "from": 16,
      "to": 23,
      "_bezier": {
        "x1": 838.3899288639552,
        "y1": -302.35993938394677,
        "cp1x": 986.1985791326479,
        "cp1y": -302.35993938394677,
        "cp2x": 940.0363915073644,
        "cp2y": -130.9401343858071,
        "x2": 1087.845041776057,
        "y2": -130.9401343858071
      }
    },
    {
      "from": 16,
      "to": 24,
      "_bezier": {
        "x1": 770.8899288639552,
        "y1": -261.35993938394677,
        "cp1x": 770.8899288639552,
        "cp1y": -159.26257544730703,
        "cp2x": 771.4744494794265,
        "cp2y": -142.75113484631305,
        "x2": 771.4744494794265,
        "y2": -40.65377090967334
      }
    },
    {
      "from": 21,
      "to": 14,
      "_bezier": {
        "x1": 1184.763348635167,
        "y1": -649.3501845813486,
        "cp1x": 1303.526094173653,
        "cp1y": -649.3501845813486,
        "cp2x": 1282.0382652482003,
        "cp2y": -721.6155743434323,
        "x2": 1400.8010107866864,
        "y2": -721.6155743434323
      }
    },
    {
      "from": 21,
      "to": 29,
      "_bezier": {
        "x1": 1127.763348635167,
        "y1": -679.3501845813486,
        "cp1x": 1127.763348635167,
        "cp1y": -829.3501845813486,
        "cp2x": 1330.511555386509,
        "cp2y": -975.9035020661479,
        "x2": 1330.511555386509,
        "y2": -1125.903502066148
      }
    },
    {
      "from": 16,
      "to": 30,
      "_bezier": {
        "x1": 770.8899288639552,
        "y1": -343.35993938394677,
        "cp1x": 770.8899288639552,
        "cp1y": -435.5253689080927,
        "cp2x": 770.8899288639552,
        "cp2y": -421.52430850021767,
        "x2": 770.8899288639552,
        "y2": -513.6897380243636
      }
    },
    {
      "from": 29,
      "to": 34,
      "_bezier": {
        "x1": 1385.511555386509,
        "y1": -1166.903502066148,
        "cp1x": 1475.0261028790137,
        "cp1y": -1166.903502066148,
        "cp2x": 1412.8001548488808,
        "cp2y": -1281.1846236121562,
        "x2": 1502.3147023413856,
        "y2": -1281.1846236121562
      }
    },
    {
      "from": 29,
      "to": 36,
      "_bezier": {
        "x1": 1385.511555386509,
        "y1": -1166.903502066148,
        "cp1x": 1477.4698151567443,
        "cp1y": -1166.903502066148,
        "cp2x": 1416.6305675711503,
        "cp2y": -1043.7315243819528,
        "x2": 1508.5888273413857,
        "y2": -1043.7315243819528
      }
    },
    {
      "from": 23,
      "to": 38,
      "_bezier": {
        "x1": 1225.845041776057,
        "y1": -130.9401343858071,
        "cp1x": 1310.0110816019264,
        "cp1y": -130.9401343858071,
        "cp2x": 1255.1507181959773,
        "cp2y": -129.8041317957719,
        "x2": 1339.3167580218467,
        "y2": -129.8041317957719
      }
    },
    {
      "from": 34,
      "to": 39,
      "_bezier": {
        "x1": 1616.3147023413856,
        "y1": -1281.1846236121562,
        "cp1x": 1705.6335322168961,
        "cp1y": -1281.1846236121562,
        "cp2x": 1635.2713243762812,
        "cp2y": -1410.8923117918746,
        "x2": 1724.5901542517918,
        "y2": -1410.8923117918746
      }
    },
    {
      "from": 34,
      "to": 40,
      "_bezier": {
        "x1": 1616.3147023413856,
        "y1": -1281.1846236121562,
        "cp1x": 1701.7986659592168,
        "cp1y": -1281.1846236121562,
        "cp2x": 1633.3577133411632,
        "cp2y": -1186.23206957898,
        "x2": 1718.8416769589944,
        "y2": -1186.23206957898
      }
    },
    {
      "from": 39,
      "to": 41,
      "_bezier": {
        "x1": 1833.5901542517918,
        "y1": -1410.8923117918746,
        "cp1x": 1913.7612690123774,
        "cp1y": -1410.8923117918746,
        "cp2x": 1852.4793673785937,
        "cp2y": -1410.8923117918746,
        "x2": 1932.6504821391793,
        "y2": -1410.8923117918746
      }
    },
    {
      "from": 63,
      "to": 64,
      "_bezier": {
        "x1": -789.7504034853443,
        "y1": 982.8477513967391,
        "cp1x": -709.4301178095018,
        "cp1y": 982.8477513967391,
        "cp2x": -767.0841586587796,
        "cp2y": 982.8477513967391,
        "x2": -686.7638729829371,
        "y2": 982.8477513967391
      }
    },
    {
      "from": 64,
      "to": 68,
      "_bezier": {
        "x1": -578.7638729829371,
        "y1": 982.8477513967391,
        "cp1x": -477.35761348504866,
        "cp1y": 952.4258735473726,
        "cp2x": -468.1763848355072,
        "cp2y": 738.4435090338314,
        "x2": -366.77012533761877,
        "y2": 708.0216311844649
      }
    },
    {
      "from": 64,
      "to": 70,
      "_bezier": {
        "x1": -578.7638729829371,
        "y1": 982.8477513967391,
        "cp1x": -428.7638729829371,
        "cp1y": 982.8477513967391,
        "cp2x": -403.6354802642878,
        "cp2y": 814.4613330443265,
        "x2": -253.63548026428782,
        "y2": 814.4613330443265
      }
    },
    {
      "from": 64,
      "to": 72,
      "_bezier": {
        "x1": -578.7638729829371,
        "y1": 982.8477513967391,
        "cp1x": -431.37249181652317,
        "cp1y": 982.8477513967391,
        "cp2x": -406.21652404874453,
        "cp2y": 970.5534135425335,
        "x2": -258.8251428823306,
        "y2": 970.5534135425335
      }
    },
    {
      "from": 64,
      "to": 73,
      "_bezier": {
        "x1": -578.7638729829371,
        "y1": 982.8477513967391,
        "cp1x": -428.7638729829371,
        "cp1y": 982.8477513967391,
        "cp2x": -408.4279987702872,
        "cp2y": 1097.9294726523863,
        "x2": -258.4279987702872,
        "y2": 1097.9294726523863
      }
    },
    {
      "from": 64,
      "to": 74,
      "_bezier": {
        "x1": -578.7638729829371,
        "y1": 982.8477513967391,
        "cp1x": -473.7638729829371,
        "cp1y": 1014.3477513967391,
        "cp2x": -443.3488030881447,
        "cp2y": 1250.143529331098,
        "x2": -338.3488030881447,
        "y2": 1281.643529331098
      }
    },
    {
      "from": 73,
      "to": 75,
      "_bezier": {
        "x1": -127.42799877028722,
        "y1": 1097.9294726523863,
        "cp1x": -46.47033710050923,
        "cp1y": 1097.9294726523863,
        "cp2x": -100.31649758010681,
        "cp2y": 1108.4294726523863,
        "x2": -19.35883591032882,
        "y2": 1108.4294726523863
      }
    },
    {
      "from": 70,
      "to": 77,
      "_bezier": {
        "x1": -155.63548026428782,
        "y1": 814.4613330443265,
        "cp1x": -60.01906265972296,
        "cp1y": 814.4613330443265,
        "cp2x": -74.06213328438163,
        "cp2y": 814.4613330443265,
        "x2": 21.55428432018323,
        "y2": 814.4613330443265
      }
    },
    {
      "from": 15,
      "to": 84,
      "_bezier": {
        "x1": 1878.0584414181203,
        "y1": -875.0537029415589,
        "cp1x": 2028.0584414181203,
        "cp1y": -875.0537029415589,
        "cp2x": 2543.405244115013,
        "cp2y": -880.4890580233555,
        "x2": 2693.405244115013,
        "y2": -880.4890580233555
      }
    },
    {
      "from": 84,
      "to": 85,
      "_bezier": {
        "x1": 2804.405244115013,
        "y1": -880.4890580233555,
        "cp1x": 2913.315366887232,
        "cp1y": -880.4890580233555,
        "cp2x": 2869.5973906683594,
        "cp2y": -1012.8825554997682,
        "x2": 2978.5075134405784,
        "y2": -1012.8825554997682
      }
    },
    {
      "from": 84,
      "to": 86,
      "_bezier": {
        "x1": 2804.405244115013,
        "y1": -880.4890580233555,
        "cp1x": 2908.360494748575,
        "cp1y": -880.4890580233555,
        "cp2x": 2883.753934755651,
        "cp2y": -789.7154820219718,
        "x2": 2987.709185389213,
        "y2": -789.7154820219718
      }
    },
    {
      "from": 24,
      "to": 88,
      "_bezier": {
        "x1": 771.4744494794265,
        "y1": 19.34622909032666,
        "cp1x": 771.4744494794265,
        "cp1y": 103.2420062641677,
        "cp2x": 661.4568425186934,
        "cp2y": 89.91354888325311,
        "x2": 661.4568425186934,
        "y2": 173.80932605709415
      }
    },
    {
      "from": 24,
      "to": 89,
      "_bezier": {
        "x1": 771.4744494794265,
        "y1": 19.34622909032666,
        "cp1x": 771.4744494794265,
        "cp1y": 109.55940689680462,
        "cp2x": 904.8374335795415,
        "cp2y": 91.20135201578843,
        "x2": 904.8374335795415,
        "y2": 181.4145298222664
      }
    },
    {
      "from": 38,
      "to": 94,
      "_bezier": {
        "x1": 1397.3167580218467,
        "y1": -99.8041317957719,
        "cp1x": 1397.3167580218467,
        "cp1y": 35.45935193303862,
        "cp2x": 1208.1658373171063,
        "cp2y": 22.446843767129963,
        "x2": 1208.1658373171063,
        "y2": 157.71032749594048
      }
    },
    {
      "from": 89,
      "to": 94,
      "_bezier": {
        "x1": 946.8374335795415,
        "y1": 209.9145298222664,
        "cp1x": 1053.0065937437087,
        "cp1y": 209.9145298222664,
        "cp2x": 1053.9966771529391,
        "cp2y": 207.21032749594048,
        "x2": 1160.1658373171063,
        "y2": 207.21032749594048
      }
    },
    {
      "from": 38,
      "to": 97,
      "_bezier": {
        "x1": 1397.3167580218467,
        "y1": -99.8041317957719,
        "cp1x": 1397.3167580218467,
        "cp1y": 36.90463212349428,
        "cp2x": 1595.1556941592876,
        "cp2y": 31.273915826447904,
        "x2": 1595.1556941592876,
        "y2": 167.98267974571408
      }
    },
    {
      "from": 21,
      "to": 99,
      "_bezier": {
        "x1": 1127.763348635167,
        "y1": -679.3501845813486,
        "cp1x": 1127.763348635167,
        "cp1y": -829.3501845813486,
        "cp2x": 906.8531345959074,
        "cp2y": -970.4940626389455,
        "x2": 906.8531345959074,
        "y2": -1120.4940626389455
      }
    },
    {
      "from": 15,
      "to": 103,
      "_bezier": {
        "x1": 1878.0584414181203,
        "y1": -875.0537029415589,
        "cp1x": 2028.0584414181203,
        "cp1y": -875.0537029415589,
        "cp2x": 2096.9155480703316,
        "cp2y": -1203.1228780955107,
        "x2": 2246.9155480703316,
        "y2": -1203.1228780955107
      }
    },
    {
      "from": 103,
      "to": 104,
      "_bezier": {
        "x1": 2350.9155480703316,
        "y1": -1203.1228780955107,
        "cp1x": 2456.0071422676183,
        "cp1y": -1203.1228780955107,
        "cp2x": 2419.2827932646096,
        "cp2y": -1339.5884647499022,
        "x2": 2524.3743874618963,
        "y2": -1339.5884647499022
      }
    },
    {
      "from": 103,
      "to": 105,
      "_bezier": {
        "x1": 2350.9155480703316,
        "y1": -1203.1228780955107,
        "cp1x": 2444.352415268547,
        "cp1y": -1203.1228780955107,
        "cp2x": 2429.94048860365,
        "cp2y": -1203.7209728534033,
        "x2": 2523.377355801865,
        "y2": -1203.7209728534033
      }
    },
    {
      "from": 103,
      "to": 106,
      "_bezier": {
        "x1": 2350.9155480703316,
        "y1": -1203.1228780955107,
        "cp1x": 2453.1961378190886,
        "cp1y": -1203.1228780955107,
        "cp2x": 2413.3694717244116,
        "cp2y": -1080.4477963951385,
        "x2": 2515.6500614731685,
        "y2": -1080.4477963951385
      }
    },
    {
      "from": 26,
      "to": 107,
      "_bezier": {
        "x1": 1407.6831165074552,
        "y1": -553.9415869027646,
        "cp1x": 1522.887248351494,
        "cp1y": -553.9415869027646,
        "cp2x": 1525.2452347055084,
        "cp2y": -506.83381556121424,
        "x2": 1640.4493665495472,
        "y2": -506.83381556121424
      }
    },
    {
      "from": 107,
      "to": 12,
      "_bezier": {
        "x1": 1735.4493665495472,
        "y1": -506.83381556121424,
        "cp1x": 1859.2491296163262,
        "cp1y": -506.83381556121424,
        "cp2x": 1836.9113942063843,
        "cp2y": -637.3290338023363,
        "x2": 1960.7111572731633,
        "y2": -637.3290338023363
      }
    },
    {
      "from": 107,
      "to": 28,
      "_bezier": {
        "x1": 1735.4493665495472,
        "y1": -506.83381556121424,
        "cp1x": 1853.6226129416348,
        "cp1y": -506.83381556121424,
        "cp2x": 1848.7901405460195,
        "cp2y": -410.20051784716645,
        "x2": 1966.963386938107,
        "y2": -410.20051784716645
      }
    },
    {
      "from": 16,
      "to": 26,
      "_bezier": {
        "x1": 838.3899288639552,
        "y1": -302.35993938394677,
        "cp1x": 988.3899288639552,
        "cp1y": -302.35993938394677,
        "cp2x": 1166.6831165074552,
        "cp2y": -553.9415869027646,
        "x2": 1316.6831165074552,
        "y2": -553.9415869027646
      }
    },
    {
      "from": 16,
      "to": 87,
      "_bezier": {
        "x1": 838.3899288639552,
        "y1": -302.35993938394677,
        "cp1x": 988.3899288639552,
        "cp1y": -302.35993938394677,
        "cp2x": 1174.5736302937275,
        "cp2y": -310.115628384188,
        "x2": 1324.5736302937275,
        "y2": -310.115628384188
      }
    },
    {
      "from": 27,
      "to": 108,
      "_bezier": {
        "x1": 1787.0977746506546,
        "y1": -302.35993938394677,
        "cp1x": 1937.0977746506546,
        "cp1y": -302.35993938394677,
        "cp2x": 2171.513283309095,
        "cp2y": -303.7797932111738,
        "x2": 2321.513283309095,
        "y2": -303.7797932111738
      }
    },
    {
      "from": 108,
      "to": 109,
      "_bezier": {
        "x1": 2412.013283309095,
        "y1": -261.7797932111738,
        "cp1x": 2412.013283309095,
        "cp1y": -132.15428112015766,
        "cp2x": 2216.6133735491053,
        "cp2y": -157.7874859005576,
        "x2": 2216.6133735491053,
        "y2": -28.161973809541475
      }
    },
    {
      "from": 108,
      "to": 110,
      "_bezier": {
        "x1": 2412.013283309095,
        "y1": -261.7797932111738,
        "cp1x": 2412.013283309095,
        "cp1y": -113.86387478704191,
        "cp2x": 2348.2492962354163,
        "cp2y": -62.41681510366203,
        "x2": 2348.2492962354163,
        "y2": 85.49910332046986
      }
    },
    {
      "from": 108,
      "to": 111,
      "_bezier": {
        "x1": 2412.013283309095,
        "y1": -261.7797932111738,
        "cp1x": 2412.013283309095,
        "cp1y": -113.19563753221837,
        "cp2x": 2508.9783347085836,
        "cp2y": -67.55989791478524,
        "x2": 2508.9783347085836,
        "y2": 81.02425776417019
      }
    },
    {
      "from": 108,
      "to": 112,
      "_bezier": {
        "x1": 2412.013283309095,
        "y1": -261.7797932111738,
        "cp1x": 2412.013283309095,
        "cp1y": -125.00262076843757,
        "cp2x": 2630.7991647286744,
        "cp2y": -145.2498258045592,
        "x2": 2630.7991647286744,
        "y2": -8.472653361822974
      }
    },
    {
      "from": 15,
      "to": 113,
      "_bezier": {
        "x1": 1878.0584414181203,
        "y1": -875.0537029415589,
        "cp1x": 2028.0584414181203,
        "cp1y": -875.0537029415589,
        "cp2x": 2047.2402038549621,
        "cp2y": -752.1647471135944,
        "x2": 2197.240203854962,
        "y2": -752.1647471135944
      }
    },
    {
      "from": 113,
      "to": 114,
      "_bezier": {
        "x1": 2300.240203854962,
        "y1": -752.1647471135944,
        "cp1x": 2431.855952019388,
        "cp1y": -752.1647471135944,
        "cp2x": 2433.9831241662528,
        "cp2y": -639.7801656955821,
        "x2": 2565.5988723306787,
        "y2": -639.7801656955821
      }
    },
    {
      "from": 113,
      "to": 115,
      "_bezier": {
        "x1": 2300.240203854962,
        "y1": -752.1647471135944,
        "cp1x": 2419.4817176445586,
        "cp1y": -752.1647471135944,
        "cp2x": 2428.17647289301,
        "cp2y": -755.0545971491568,
        "x2": 2547.4179866826066,
        "y2": -755.0545971491568
      }
    },
    {
      "from": 113,
      "to": 116,
      "_bezier": {
        "x1": 2248.740203854962,
        "y1": -723.6647471135944,
        "cp1x": 2248.740203854962,
        "cp1y": -635.8934146103769,
        "cp2x": 2249.555710955165,
        "cp2y": -617.662169888675,
        "x2": 2249.555710955165,
        "y2": -529.8908373854574
      }
    },
    {
      "from": 113,
      "to": 117,
      "_bezier": {
        "x1": 2300.240203854962,
        "y1": -752.1647471135944,
        "cp1x": 2385.0011501664703,
        "cp1y": -726.7364632201419,
        "cp2x": 2381.2014184784457,
        "cp2y": -548.4766837181232,
        "x2": 2465.962364789954,
        "y2": -523.0483998246707
      }
    },
    {
      "from": 38,
      "to": 118,
      "_bezier": {
        "x1": 1397.3167580218467,
        "y1": -99.8041317957719,
        "cp1x": 1397.3167580218467,
        "cp1y": 50.195868204228105,
        "cp2x": 1403.218946641484,
        "cp2y": 167.0498908208346,
        "x2": 1403.218946641484,
        "y2": 317.0498908208346
      }
    }
  ],
  "nodeIdCounter": 120,
  "view": {
    "scale": 0.8061665432724339,
    "panX": -952.0968656718046,
    "panY": 1539.306080813815
  },
  "exportedAt": "2025-12-25T10:06:01.816Z",
  "version": "2.0"
}